setup.py
SizeDupe_Reporter.egg-info/PKG-INFO
SizeDupe_Reporter.egg-info/SOURCES.txt
SizeDupe_Reporter.egg-info/dependency_links.txt
SizeDupe_Reporter.egg-info/entry_points.txt
SizeDupe_Reporter.egg-info/requires.txt
SizeDupe_Reporter.egg-info/top_level.txt
sizedupe/__init__.py
sizedupe/sizedupe.py
