Metadata-Version: 1.0
Name: SizeDupe-Reporter
Version: 0.9.1
Summary: File/directory size/duplicate scanning and reporting tool.
Home-page: UNKNOWN
Author: Joe Koberg
Author-email: joe@osoft.us
License: GPLv3
Keywords: space free disk filelight philesight dupe duplicate
Platform: UNKNOWN
